Metadata-Version: 2.1
Name: odoo12-addon-module-auto-update
Version: 12.0.2.0.7
Summary: Automatically update Odoo modules
Home-page: https://github.com/OCA/server-tools
Author: LasLabs, Juan José Scarafía, Tecnativa, ACSONE SA/NV, Odoo Community Association (OCA)
Author-email: support@odoo-community.org
License: LGPL-3
Platform: UNKNOWN
Classifier: Programming Language :: Python
Classifier: Framework :: Odoo
Classifier: Framework :: Odoo :: 12.0
Classifier: License :: OSI Approved :: GNU Lesser General Public License v3 (LGPLv3)
Classifier: Development Status :: 5 - Production/Stable
Requires-Python: >=3.5
Requires-Dist: odoo <12.1dev,>=12.0a
